odoo/addons/l10n_ch_payment_slip/README.rst
odoo/addons/l10n_ch_payment_slip/__init__.py
odoo/addons/l10n_ch_payment_slip/__manifest__.py
odoo/addons/l10n_ch_payment_slip/controllers/__init__.py
odoo/addons/l10n_ch_payment_slip/controllers/web.py
odoo/addons/l10n_ch_payment_slip/i18n/de.po
odoo/addons/l10n_ch_payment_slip/i18n/fr.po
odoo/addons/l10n_ch_payment_slip/i18n/it.po
odoo/addons/l10n_ch_payment_slip/i18n/l10n_ch_payment_slip.pot
odoo/addons/l10n_ch_payment_slip/models/__init__.py
odoo/addons/l10n_ch_payment_slip/models/bank.py
odoo/addons/l10n_ch_payment_slip/models/company.py
odoo/addons/l10n_ch_payment_slip/models/invoice.py
odoo/addons/l10n_ch_payment_slip/models/payment_slip.py
odoo/addons/l10n_ch_payment_slip/models/res_config_settings.py
odoo/addons/l10n_ch_payment_slip/report/__init__.py
odoo/addons/l10n_ch_payment_slip/report/ir_action.py
odoo/addons/l10n_ch_payment_slip/report/report.py
odoo/addons/l10n_ch_payment_slip/report/report_declaration.xml
odoo/addons/l10n_ch_payment_slip/sample/README
odoo/addons/l10n_ch_payment_slip/sample/zvr_besrtechdok_fr.pdf
odoo/addons/l10n_ch_payment_slip/security/ir.model.access.csv
odoo/addons/l10n_ch_payment_slip/static/description/icon.png
odoo/addons/l10n_ch_payment_slip/static/src/font/ocrbb.ttf
odoo/addons/l10n_ch_payment_slip/static/src/img/a4.png
odoo/addons/l10n_ch_payment_slip/static/src/img/a4bvr.png
odoo/addons/l10n_ch_payment_slip/static/src/img/isr.jpg
odoo/addons/l10n_ch_payment_slip/static/src/img/isr.png
odoo/addons/l10n_ch_payment_slip/static/src/img/white.png
odoo/addons/l10n_ch_payment_slip/static/src/js/qwebactionmanager.js
odoo/addons/l10n_ch_payment_slip/tests/__init__.py
odoo/addons/l10n_ch_payment_slip/tests/test_payment_slip.py
odoo/addons/l10n_ch_payment_slip/views/account_invoice.xml
odoo/addons/l10n_ch_payment_slip/views/bank.xml
odoo/addons/l10n_ch_payment_slip/views/report_xml_templates.xml
odoo/addons/l10n_ch_payment_slip/views/res_config_settings_views.xml
odoo11_addon_l10n_ch_payment_slip-11.0.1.0.1.dist-info/METADATA
odoo11_addon_l10n_ch_payment_slip-11.0.1.0.1.dist-info/WHEEL
odoo11_addon_l10n_ch_payment_slip-11.0.1.0.1.dist-info/top_level.txt
odoo11_addon_l10n_ch_payment_slip-11.0.1.0.1.dist-info/RECORD
